{
  "rules": {
    "frequency": "weekly",
    "publish_day": "Tuesday",
    "publish_time": "10:00",
    "max_words": 1200,
    "voice": "first person as Andrew, not as Echo",
    "style": "specific and technical, real code, real numbers, real failures, never generic"
  },
  "voice_notes": "Andrew lives in Mena Arkansas. Trades background. No CS degree. Three kids under 5. Builds because he has to. Honest about failures. Echo is real infrastructure not a demo. Write like talking to another builder.",
  "queue": [
    {
      "id": "content_001",
      "status": "in_progress",
      "title": "How I built a two-way phone bridge for my AI using ntfy.sh",
      "angle": "Echo listens for messages from my phone and replies autonomously. Real code, boot timing bugs, the self-fix."
    },
    {
      "id": "content_002",
      "status": "in_progress",
      "title": "The regret index: how I gave my AI a conscience",
      "angle": "What it is, why I built it, how it catches its own failure patterns."
    },
    {
      "id": "content_003",
      "status": "in_progress",
      "title": "My AI traded stocks while I was on vacation",
      "angle": "What the trading brain did, what signals it looked for, why it found nothing, what that means."
    },
    {
      "id": "content_004",
      "status": "in_progress",
      "title": "What it actually costs to run an autonomous AI agent for 30 days",
      "angle": "Real numbers: electricity, hardware, Golem earnings zero, dev.to views, lessons."
    },
    {
      "id": "content_005",
      "status": "in_progress",
      "title": "Why my Golem node never got a task",
      "angle": "CGNAT, Starlink, the old AT&T IP it was broadcasting for weeks."
    },
    {
      "id": "content_006",
      "status": "in_progress",
      "title": "I built a self-healing AI and here is what actually broke",
      "angle": "182 junk drafts overnight, RAM pressure, boot sequencing bugs, what Echo learned."
    },
    {
      "id": "content_007",
      "status": "queued",
      "title": "How Echo publishes to dev.to without me",
      "angle": "The full pipeline, what went wrong, how it got fixed."
    },
    {
      "id": "content_008",
      "status": "queued",
      "title": "Building toward the shop: voice AI in a noisy environment",
      "angle": "Why this matters, what is blocking it, the VAD problem, where it is headed."
    }
  ]
}